[1,["05c6ccMCJCqb6D3Uvla4vN@6c48a","27SPzi5r1FjJ7dSeNdPXn2@6c48a","37aOjqvOJNX6Xvqz/C/1BX@6c48a","3e72F0NbRAwoD2NNa7UljL@6c48a","43u85ixoFAL40Befuf/N9B@6c48a","59P86dI3xF0ZhHrFBYN33g@6c48a","5awWMG4LJJwYoROoTJmqtw@6c48a","5bFwglpzRCkb8B7GgxKQj6@6c48a","81ylT9GCNOfq6ebo2FHJru@6c48a","86DaXtQPZAMIz9gJshJqCk@6c48a","88HLajEIZP/bY4OsxpiqEr@6c48a","96l1vyaNNHvoL9ly5/8JgF@6c48a","a9gYhdg41DTKpCkRiH5L6A@6c48a","b1BMffrLhK4rJsI6VkjUTL@6c48a","b8WnSUMQBNK6uMcWU8c9dA@6c48a","ccpdTSsSZLJLXV81sDtzIP@6c48a","d3zmEx+aNNYZ4i5ZBnRxs9@6c48a","e8m6TGTqpK9I8bMec4yOrg@6c48a","f3TOSzNElLpoB5ztBAkgvL@6c48a","feAVNLD8VOQIUEh9Pq6B6R@6c48a"],["_textureSource"],["cc.SpriteFrame"],0,[[[{"name":"Hero_0007_Слой-9","rect":{"x":0,"y":0,"width":126,"height":252},"offset":{"x":0,"y":0},"originalSize":{"width":126,"height":252},"rotated":false,"capInsets":[0,0,0,0],"vertices":{"rawPosition":[-63,-126,0,63,-126,0,-63,126,0,63,126,0],"indexes":[0,1,2,2,1,3],"uv":[0,252,126,252,0,0,126,0],"nuv":[0,0,1,0,0,1,1,1],"minPos":{"x":-63,"y":-126,"z":0},"maxPos":{"x":63,"y":126,"z":0}},"packable":true,"pixelsToUnit":100,"pivot":{"x":0.5,"y":0.5},"meshType":0}],[0],0,[0],[0],[0]],[[{"name":"Hero_0016_Слой-18","rect":{"x":0,"y":0,"width":126,"height":252},"offset":{"x":0,"y":0},"originalSize":{"width":126,"height":252},"rotated":false,"capInsets":[0,0,0,0],"vertices":{"rawPosition":[-63,-126,0,63,-126,0,-63,126,0,63,126,0],"indexes":[0,1,2,2,1,3],"uv":[0,252,126,252,0,0,126,0],"nuv":[0,0,1,0,0,1,1,1],"minPos":{"x":-63,"y":-126,"z":0},"maxPos":{"x":63,"y":126,"z":0}},"packable":true,"pixelsToUnit":100,"pivot":{"x":0.5,"y":0.5},"meshType":0}],[0],0,[0],[0],[1]],[[{"name":"Hero_0009_Слой-11","rect":{"x":0,"y":0,"width":126,"height":254},"offset":{"x":0,"y":0},"originalSize":{"width":126,"height":254},"rotated":false,"capInsets":[0,0,0,0],"vertices":{"rawPosition":[-63,-127,0,63,-127,0,-63,127,0,63,127,0],"indexes":[0,1,2,2,1,3],"uv":[0,254,126,254,0,0,126,0],"nuv":[0,0,1,0,0,1,1,1],"minPos":{"x":-63,"y":-127,"z":0},"maxPos":{"x":63,"y":127,"z":0}},"packable":true,"pixelsToUnit":100,"pivot":{"x":0.5,"y":0.5},"meshType":0}],[0],0,[0],[0],[2]],[[{"name":"Hero_0015_Слой-17","rect":{"x":0,"y":0,"width":126,"height":253},"offset":{"x":0,"y":0},"originalSize":{"width":126,"height":253},"rotated":false,"capInsets":[0,0,0,0],"vertices":{"rawPosition":[-63,-126.5,0,63,-126.5,0,-63,126.5,0,63,126.5,0],"indexes":[0,1,2,2,1,3],"uv":[0,253,126,253,0,0,126,0],"nuv":[0,0,1,0,0,1,1,1],"minPos":{"x":-63,"y":-126.5,"z":0},"maxPos":{"x":63,"y":126.5,"z":0}},"packable":true,"pixelsToUnit":100,"pivot":{"x":0.5,"y":0.5},"meshType":0}],[0],0,[0],[0],[3]],[[{"name":"Hero_0032_Слой-34","rect":{"x":0,"y":0,"width":126,"height":252},"offset":{"x":0,"y":0},"originalSize":{"width":126,"height":252},"rotated":false,"capInsets":[0,0,0,0],"vertices":{"rawPosition":[-63,-126,0,63,-126,0,-63,126,0,63,126,0],"indexes":[0,1,2,2,1,3],"uv":[0,252,126,252,0,0,126,0],"nuv":[0,0,1,0,0,1,1,1],"minPos":{"x":-63,"y":-126,"z":0},"maxPos":{"x":63,"y":126,"z":0}},"packable":true,"pixelsToUnit":100,"pivot":{"x":0.5,"y":0.5},"meshType":0}],[0],0,[0],[0],[4]],[[{"name":"Hero_0030_Слой-32","rect":{"x":0,"y":0,"width":126,"height":252},"offset":{"x":0,"y":0},"originalSize":{"width":126,"height":252},"rotated":false,"capInsets":[0,0,0,0],"vertices":{"rawPosition":[-63,-126,0,63,-126,0,-63,126,0,63,126,0],"indexes":[0,1,2,2,1,3],"uv":[0,252,126,252,0,0,126,0],"nuv":[0,0,1,0,0,1,1,1],"minPos":{"x":-63,"y":-126,"z":0},"maxPos":{"x":63,"y":126,"z":0}},"packable":true,"pixelsToUnit":100,"pivot":{"x":0.5,"y":0.5},"meshType":0}],[0],0,[0],[0],[5]],[[{"name":"Hero_0017_Слой-19","rect":{"x":0,"y":0,"width":126,"height":252},"offset":{"x":0,"y":0},"originalSize":{"width":126,"height":252},"rotated":false,"capInsets":[0,0,0,0],"vertices":{"rawPosition":[-63,-126,0,63,-126,0,-63,126,0,63,126,0],"indexes":[0,1,2,2,1,3],"uv":[0,252,126,252,0,0,126,0],"nuv":[0,0,1,0,0,1,1,1],"minPos":{"x":-63,"y":-126,"z":0},"maxPos":{"x":63,"y":126,"z":0}},"packable":true,"pixelsToUnit":100,"pivot":{"x":0.5,"y":0.5},"meshType":0}],[0],0,[0],[0],[6]],[[{"name":"Hero_0012_Слой-14","rect":{"x":0,"y":0,"width":126,"height":253},"offset":{"x":0,"y":0},"originalSize":{"width":126,"height":253},"rotated":false,"capInsets":[0,0,0,0],"vertices":{"rawPosition":[-63,-126.5,0,63,-126.5,0,-63,126.5,0,63,126.5,0],"indexes":[0,1,2,2,1,3],"uv":[0,253,126,253,0,0,126,0],"nuv":[0,0,1,0,0,1,1,1],"minPos":{"x":-63,"y":-126.5,"z":0},"maxPos":{"x":63,"y":126.5,"z":0}},"packable":true,"pixelsToUnit":100,"pivot":{"x":0.5,"y":0.5},"meshType":0}],[0],0,[0],[0],[7]],[[{"name":"Hero_0031_Слой-33","rect":{"x":0,"y":0,"width":126,"height":252},"offset":{"x":0,"y":0},"originalSize":{"width":126,"height":252},"rotated":false,"capInsets":[0,0,0,0],"vertices":{"rawPosition":[-63,-126,0,63,-126,0,-63,126,0,63,126,0],"indexes":[0,1,2,2,1,3],"uv":[0,252,126,252,0,0,126,0],"nuv":[0,0,1,0,0,1,1,1],"minPos":{"x":-63,"y":-126,"z":0},"maxPos":{"x":63,"y":126,"z":0}},"packable":true,"pixelsToUnit":100,"pivot":{"x":0.5,"y":0.5},"meshType":0}],[0],0,[0],[0],[8]],[[{"name":"Hero_0021_Слой-23","rect":{"x":0,"y":0,"width":126,"height":252},"offset":{"x":0,"y":0},"originalSize":{"width":126,"height":252},"rotated":false,"capInsets":[0,0,0,0],"vertices":{"rawPosition":[-63,-126,0,63,-126,0,-63,126,0,63,126,0],"indexes":[0,1,2,2,1,3],"uv":[0,252,126,252,0,0,126,0],"nuv":[0,0,1,0,0,1,1,1],"minPos":{"x":-63,"y":-126,"z":0},"maxPos":{"x":63,"y":126,"z":0}},"packable":true,"pixelsToUnit":100,"pivot":{"x":0.5,"y":0.5},"meshType":0}],[0],0,[0],[0],[9]],[[{"name":"Hero_0010_Слой-12","rect":{"x":0,"y":0,"width":126,"height":253},"offset":{"x":0,"y":0},"originalSize":{"width":126,"height":253},"rotated":false,"capInsets":[0,0,0,0],"vertices":{"rawPosition":[-63,-126.5,0,63,-126.5,0,-63,126.5,0,63,126.5,0],"indexes":[0,1,2,2,1,3],"uv":[0,253,126,253,0,0,126,0],"nuv":[0,0,1,0,0,1,1,1],"minPos":{"x":-63,"y":-126.5,"z":0},"maxPos":{"x":63,"y":126.5,"z":0}},"packable":true,"pixelsToUnit":100,"pivot":{"x":0.5,"y":0.5},"meshType":0}],[0],0,[0],[0],[10]],[[{"name":"Hero_0038_Слой-40","rect":{"x":0,"y":0,"width":126,"height":250},"offset":{"x":0,"y":0},"originalSize":{"width":126,"height":250},"rotated":false,"capInsets":[0,0,0,0],"vertices":{"rawPosition":[-63,-125,0,63,-125,0,-63,125,0,63,125,0],"indexes":[0,1,2,2,1,3],"uv":[0,250,126,250,0,0,126,0],"nuv":[0,0,1,0,0,1,1,1],"minPos":{"x":-63,"y":-125,"z":0},"maxPos":{"x":63,"y":125,"z":0}},"packable":true,"pixelsToUnit":100,"pivot":{"x":0.5,"y":0.5},"meshType":0}],[0],0,[0],[0],[11]],[[{"name":"Hero_0022_Слой-24","rect":{"x":0,"y":0,"width":126,"height":253},"offset":{"x":0,"y":0},"originalSize":{"width":126,"height":253},"rotated":false,"capInsets":[0,0,0,0],"vertices":{"rawPosition":[-63,-126.5,0,63,-126.5,0,-63,126.5,0,63,126.5,0],"indexes":[0,1,2,2,1,3],"uv":[0,253,126,253,0,0,126,0],"nuv":[0,0,1,0,0,1,1,1],"minPos":{"x":-63,"y":-126.5,"z":0},"maxPos":{"x":63,"y":126.5,"z":0}},"packable":true,"pixelsToUnit":100,"pivot":{"x":0.5,"y":0.5},"meshType":0}],[0],0,[0],[0],[12]],[[{"name":"Hero_0029_Слой-31","rect":{"x":0,"y":0,"width":126,"height":253},"offset":{"x":0,"y":0},"originalSize":{"width":126,"height":253},"rotated":false,"capInsets":[0,0,0,0],"vertices":{"rawPosition":[-63,-126.5,0,63,-126.5,0,-63,126.5,0,63,126.5,0],"indexes":[0,1,2,2,1,3],"uv":[0,253,126,253,0,0,126,0],"nuv":[0,0,1,0,0,1,1,1],"minPos":{"x":-63,"y":-126.5,"z":0},"maxPos":{"x":63,"y":126.5,"z":0}},"packable":true,"pixelsToUnit":100,"pivot":{"x":0.5,"y":0.5},"meshType":0}],[0],0,[0],[0],[13]],[[{"name":"Hero_0023_Слой-25","rect":{"x":0,"y":0,"width":126,"height":252},"offset":{"x":0,"y":0},"originalSize":{"width":126,"height":252},"rotated":false,"capInsets":[0,0,0,0],"vertices":{"rawPosition":[-63,-126,0,63,-126,0,-63,126,0,63,126,0],"indexes":[0,1,2,2,1,3],"uv":[0,252,126,252,0,0,126,0],"nuv":[0,0,1,0,0,1,1,1],"minPos":{"x":-63,"y":-126,"z":0},"maxPos":{"x":63,"y":126,"z":0}},"packable":true,"pixelsToUnit":100,"pivot":{"x":0.5,"y":0.5},"meshType":0}],[0],0,[0],[0],[14]],[[{"name":"Hero_0008_Слой-10","rect":{"x":0,"y":0,"width":126,"height":253},"offset":{"x":0,"y":0},"originalSize":{"width":126,"height":253},"rotated":false,"capInsets":[0,0,0,0],"vertices":{"rawPosition":[-63,-126.5,0,63,-126.5,0,-63,126.5,0,63,126.5,0],"indexes":[0,1,2,2,1,3],"uv":[0,253,126,253,0,0,126,0],"nuv":[0,0,1,0,0,1,1,1],"minPos":{"x":-63,"y":-126.5,"z":0},"maxPos":{"x":63,"y":126.5,"z":0}},"packable":true,"pixelsToUnit":100,"pivot":{"x":0.5,"y":0.5},"meshType":0}],[0],0,[0],[0],[15]],[[{"name":"Hero_0020_Слой-22","rect":{"x":0,"y":0,"width":126,"height":252},"offset":{"x":0,"y":0},"originalSize":{"width":126,"height":252},"rotated":false,"capInsets":[0,0,0,0],"vertices":{"rawPosition":[-63,-126,0,63,-126,0,-63,126,0,63,126,0],"indexes":[0,1,2,2,1,3],"uv":[0,252,126,252,0,0,126,0],"nuv":[0,0,1,0,0,1,1,1],"minPos":{"x":-63,"y":-126,"z":0},"maxPos":{"x":63,"y":126,"z":0}},"packable":true,"pixelsToUnit":100,"pivot":{"x":0.5,"y":0.5},"meshType":0}],[0],0,[0],[0],[16]],[[{"name":"Hero_0033_Слой-35","rect":{"x":0,"y":0,"width":126,"height":252},"offset":{"x":0,"y":0},"originalSize":{"width":126,"height":252},"rotated":false,"capInsets":[0,0,0,0],"vertices":{"rawPosition":[-63,-126,0,63,-126,0,-63,126,0,63,126,0],"indexes":[0,1,2,2,1,3],"uv":[0,252,126,252,0,0,126,0],"nuv":[0,0,1,0,0,1,1,1],"minPos":{"x":-63,"y":-126,"z":0},"maxPos":{"x":63,"y":126,"z":0}},"packable":true,"pixelsToUnit":100,"pivot":{"x":0.5,"y":0.5},"meshType":0}],[0],0,[0],[0],[17]],[[{"name":"Hero_0028_Слой-30","rect":{"x":0,"y":0,"width":126,"height":253},"offset":{"x":0,"y":0},"originalSize":{"width":126,"height":253},"rotated":false,"capInsets":[0,0,0,0],"vertices":{"rawPosition":[-63,-126.5,0,63,-126.5,0,-63,126.5,0,63,126.5,0],"indexes":[0,1,2,2,1,3],"uv":[0,253,126,253,0,0,126,0],"nuv":[0,0,1,0,0,1,1,1],"minPos":{"x":-63,"y":-126.5,"z":0},"maxPos":{"x":63,"y":126.5,"z":0}},"packable":true,"pixelsToUnit":100,"pivot":{"x":0.5,"y":0.5},"meshType":0}],[0],0,[0],[0],[18]],[[{"name":"Hero_0024_Слой-26","rect":{"x":0,"y":0,"width":126,"height":252},"offset":{"x":0,"y":0},"originalSize":{"width":126,"height":252},"rotated":false,"capInsets":[0,0,0,0],"vertices":{"rawPosition":[-63,-126,0,63,-126,0,-63,126,0,63,126,0],"indexes":[0,1,2,2,1,3],"uv":[0,252,126,252,0,0,126,0],"nuv":[0,0,1,0,0,1,1,1],"minPos":{"x":-63,"y":-126,"z":0},"maxPos":{"x":63,"y":126,"z":0}},"packable":true,"pixelsToUnit":100,"pivot":{"x":0.5,"y":0.5},"meshType":0}],[0],0,[0],[0],[19]]]]
